s3_last_modified_objects/__init__.py
s3_last_modified_objects/s3_objects.py
s3_last_modified_objects-0.0.3.dist-info/METADATA
s3_last_modified_objects-0.0.3.dist-info/WHEEL
s3_last_modified_objects-0.0.3.dist-info/top_level.txt
s3_last_modified_objects-0.0.3.dist-info/RECORD
