Metadata-Version: 2.1
Name: s3-last-modified-objects
Version: 0.0.3
Summary: Utility modules for the s3 get s3 last modified objects tasks.
Author: Momataj Begum
Author-email: momataj.momo@gmail.com
License: UNKNOWN
Platform: UNKNOWN
Classifier: Programming Language :: Python :: 3
Classifier: License :: OSI Approved :: MIT License
Classifier: Operating System :: OS Independent
Requires-Python: >=3.6
Requires-Dist: boto3
